{"id": "34u5o9", "post_id": "reddit/dataisugly/34u5o9", "image_name": "34u5o9_0", "image_path": "preview/34u5o9_0.jpg", "thumbnail_path": "thumbnail/34u5o9_0.jpg", "datetime": 1430756116.0, "url": "https://reddit.com/r/dataisugly/comments/34u5o9/a_comparison_of_programming_languages_by/", "title": "A comparison of programming languages by popularity. Overlapping bubbles because why not?", "author": "", "popularity_score": 560, "phash": "af9695e140e611b7", "duplicated_images": ["reddit/dataisugly/8vm5cw_0", "reddit/dataisugly/5ipia2_0", "reddit/dataisugly/356rfo_0"], "duplicated_posts": [{"url": "https://reddit.com/r/dataisugly/comments/356rfo/a_comparison_of_the_most_popular_programming/", "title": "A comparison of the most popular programming languages of 2015. Needs more overlapping bubbles.", "author": "bubbles212", "post_id": "reddit/dataisugly/356rfo", "datetime": 1431014371.0}, {"url": "https://reddit.com/r/dataisugly/comments/5ipia2/when_a_pie_chart_is_not_hip_enough/", "title": "When a pie chart is not hip enough", "author": "iamnottravis", "post_id": "reddit/dataisugly/5ipia2", "datetime": 1481909521.0}, {"url": "https://reddit.com/r/dataisugly/comments/8vm5cw/its_like_a_pie_chart_and_venn_diagram_give_birth/", "title": "It's like a pie chart and Venn diagram give birth to agar.io", "author": "flipkitty", "post_id": "reddit/dataisugly/8vm5cw", "datetime": 1530564668.0}], "labels": ["data:categorical", "data:percentage", "domain:computer", "effect:confuesed", "fault:position", "form:bubblechart"], "remarks": "What does overlapping mean?"}