{"id": "6wn31m", "post_id": "reddit/dataisugly/6wn31m", "image_name": "6wn31m_0", "image_path": "preview/6wn31m_0.jpg", "thumbnail_path": "thumbnail/6wn31m_0.jpg", "datetime": 1503960601.0, "url": "https://reddit.com/r/dataisugly/comments/6wn31m/my_schools_election_results_in_the_yearbook/", "title": "My school's election results in the yearbook", "author": "", "popularity_score": 553, "phash": "97abd0a4ea742a5a", "duplicated_images": [], "duplicated_posts": [], "labels": ["data:categorical", "data:percentage", "domain:politics", "effect:distorted", "fault:axis:truncated", "form:barchart"], "remarks": "1% is a lot."}