{"id": "6z2hc0", "image_name": "6z2hc0_0", "image_path": "preview/6z2hc0_0.gif", "thumbnail_path": "thumbnail/6z2hc0_0.jpg", "datetime": 1504972956.0, "url": "https://reddit.com/r/dataisugly/comments/6z2hc0/predicted_vs_actual_path_of_irma_15k_upvotes_on/", "title": "Predicted vs actual path of Irma. 15k upvotes on r/dataisbeautiful Doesn't help to tell the difference at all.", "author": "ganjawarriorpro", "source": "dataisugly", "source_url": "https://www.reddit.com/r/dataisugly", "source_platform": "reddit", "popularity_score": 567, "phash": "950a3f54f0c7a15e", "duplicated_images": [], "labels": ["data:geospatial", "fault:animation", "form:map", "layout:animated"], "remarks": "The revised version is much better: https://i.imgur.com/SRO9BzA.jpg"}