{"id": "7105ux", "post_id": "reddit/dataisugly/7105ux", "image_name": "7105ux_0", "image_path": "preview/7105ux_0.jpg", "thumbnail_path": "thumbnail/7105ux_0.jpg", "datetime": 1505789996.0, "url": "https://reddit.com/r/dataisugly/comments/7105ux/from_my_business_society_texbook/", "title": "From my Business & Society Texbook", "author": "Axillus", "popularity_score": 277, "phash": "b3a3cc1c47e13173", "duplicated_images": [], "duplicated_posts": [], "labels": ["data:categorical", "data:percentage", "domain:business", "effect:distorted", "fault:percentage:sum", "form:piechart", "media:printed"], "remarks": "Percentage not 100%"}