{"id": "7fafjk", "post_id": "reddit/dataisugly/7fafjk", "image_name": "7fafjk_0", "image_path": "preview/7fafjk_0.jpg", "thumbnail_path": "thumbnail/7fafjk_0.jpg", "datetime": 1511558177.0, "url": "https://reddit.com/r/dataisugly/comments/7fafjk/a_3d_bar_chart_with_negative_values/", "title": "A 3D bar chart with negative values!", "author": "binarySwordsman", "popularity_score": 287, "phash": "e5c89a74ce29d12e", "duplicated_images": [], "duplicated_posts": [], "labels": ["data:categorical", "data:quantitative", "data:timeseries", "domain:sports", "effect:distorted", "fault:3d", "form:stackedbarchart"], "remarks": "3D. I cannot tell where is zero and where is negative."}