{"id": "7iqbmh", "post_id": "reddit/dataisugly/7iqbmh", "image_name": "7iqbmh_0", "image_path": "preview/7iqbmh_0.png", "thumbnail_path": "thumbnail/7iqbmh_0.jpg", "datetime": 1512862913.0, "url": "https://reddit.com/r/dataisugly/comments/7iqbmh/facebook_insights_w_useless_axis_labels/", "title": "Facebook Insights w/ useless axis labels", "author": "danielnorton", "popularity_score": 278, "phash": "8707073564d1b3e7", "duplicated_images": [], "duplicated_posts": [], "labels": ["data:quantitative", "data:timeseries", "domain:business", "effect:confuesed", "fault:axis:incorrectlabel", "form:linechart"], "remarks": "2.4K, 2.4K, 2.4K."}