{"id": "7ssujs", "post_id": "reddit/dataisugly/7ssujs", "image_name": "7ssujs_0", "image_path": "preview/7ssujs_0.png", "thumbnail_path": "thumbnail/7ssujs_0.jpg", "datetime": 1516847854.0, "url": "https://reddit.com/r/dataisugly/comments/7ssujs/thats_a_lot_of_vietnamese_wait/", "title": "That's a lot of Vietnamese! -Wait", "author": "djbigted", "popularity_score": 246, "phash": "b96bc49993a62734", "duplicated_images": [], "duplicated_posts": [], "labels": ["data:categorical", "data:percentage", "data:quantitative", "domain:international", "effect:confuesed", "fault:betteralternative", "form:unknown"], "remarks": "Confusing growth rate and absolute number. There are better alternatives."}