{"id": "8p0se2", "image_name": "8p0se2_0", "image_path": "bad-vis-images/preview/8p0se2_0.png", "thumbnail_path": "bad-vis-images/thumbnail/8p0se2_0.jpg", "datetime": 1528293267.0, "url": "https://reddit.com/r/dataisugly/comments/8p0se2/graph_of_ops_gpa_per_semester_in_college_xpost/", "title": "Graph of OP's GPA per semester in college (x-post /r/dataisbeautiful) [OC]", "author": "", "source": "dataisugly", "source_url": "https://www.reddit.com/r/dataisugly", "source_platform": "reddit", "popularity_score": 56240, "phash": "ea9335c025ec3d0f", "labels": ["data:quantitative", "data:timeseries", "fault:betteralternative", "form:linechart"], "remarks": ""}