{"id": "93bq03", "image_name": "93bq03_0", "image_path": "preview/93bq03_0.jpg", "thumbnail_path": "thumbnail/93bq03_0.jpg", "datetime": 1533015007.0, "url": "https://reddit.com/r/dataisugly/comments/93bq03/i_feel_bad_for_this_one_but_12/", "title": "I feel bad for this one, but... >12?", "author": "SeaBourneOwl", "source": "dataisugly", "source_url": "https://www.reddit.com/r/dataisugly", "source_platform": "reddit", "popularity_score": 70, "phash": "da96e5c1134c9e1e", "duplicated_images": ["reddit/dataisbeautiful/9392i8_0"], "labels": ["data:accumulated", "fault:label", "form:barchart"], "remarks": ""}