{"id": "9vjfaj", "post_id": "reddit/dataisugly/9vjfaj", "image_name": "9vjfaj_0", "image_path": "preview/9vjfaj_0.jpg", "thumbnail_path": "thumbnail/9vjfaj_0.jpg", "datetime": 1541760058.0, "url": "https://reddit.com/r/dataisugly/comments/9vjfaj/op_found_this_atrocity_in_his_senior_yearbook/", "title": "OP Found this ATROCITY in his senior yearbook", "author": "", "popularity_score": 78, "phash": "c6c93f496e60c837", "duplicated_images": ["reddit/CrappyDesign/9vdmq8_0", "reddit/dataisugly/9vmdhi_0"], "duplicated_posts": [{"url": "https://reddit.com/r/dataisugly/comments/9vmdhi/my_yearbook_posted_in_rcrappy_design_but_was/", "title": "My yearbook (posted in r/crappy design, but was advised to post here)", "author": "aceguy45", "post_id": "reddit/dataisugly/9vmdhi", "datetime": 1541784340.0}, {"url": "https://reddit.com/r/CrappyDesign/comments/9vdmq8/found_this_atrocity_in_my_senior_yearbook/", "title": "Found this ATROCITY in my senior yearbook", "author": "aceguy45", "post_id": "reddit/CrappyDesign/9vdmq8", "datetime": 1541709006.0}], "labels": ["data:categorical", "data:percentage", "domain:personal", "effect:distorted", "fault:scale:inconsistent", "form:barchart", "media:printed"], "remarks": "20% is more than 35%."}