{"id": "alv43x", "post_id": "reddit/dataisugly/alv43x", "image_name": "alv43x_0", "image_path": "preview/alv43x_0.gif", "thumbnail_path": "thumbnail/alv43x_0.jpg", "datetime": 1548973785.0, "url": "https://reddit.com/r/dataisugly/comments/alv43x/the_original_map_which_is_the_wellknown_mercator/", "title": "The original map (which is the well-known Mercator projection) itself is deformed by nature.", "author": "iqueerified", "popularity_score": 145, "phash": "e8b4cb83246cb95b", "duplicated_images": ["reddit/dataisbeautiful/alr6jt_0"], "duplicated_posts": [{"url": "https://reddit.com/r/dataisbeautiful/comments/alr6jt/countries_scaled_by_total_co2_emissions_1971_to/", "title": "Countries scaled by total CO2 emissions 1971 to 2014 [OC]", "author": "neilrkaye", "post_id": "reddit/dataisbeautiful/alr6jt", "datetime": 1548952027.0}], "labels": ["data:geospatial", "data:quantitative", "domain:environment", "effect:confuesed", "fault:animation", "fault:mapprojection", "form:choropleth", "layout:animated"], "remarks": "Map projection\nAnimation"}