{"id": "bcd1gs", "post_id": "reddit/dataisugly/bcd1gs", "image_name": "bcd1gs_0", "image_path": "preview/bcd1gs_0.png", "thumbnail_path": "thumbnail/bcd1gs_0.jpg", "datetime": 1555072510.0, "url": "https://reddit.com/r/dataisugly/comments/bcd1gs/business_is_looking_up_now_let_me_tweak_this_scale/", "title": "Business is looking up! Now let me tweak this scale...", "author": "zonination", "popularity_score": 324, "phash": "c61aa1e9792d7e90", "duplicated_images": [], "duplicated_posts": [], "labels": ["data:quantitative", "data:timeseries", "domain:business", "effect:distorted", "fault:scale:inconsistent", "form:barchart", "form:pictogram", "layout:juxtaposition"], "remarks": "7494 is shorter than 7222."}