{"id": "bd4rl1", "post_id": "reddit/dataisugly/bd4rl1", "image_name": "bd4rl1_0", "image_path": "preview/bd4rl1_0.png", "thumbnail_path": "thumbnail/bd4rl1_0.jpg", "datetime": 1555260808.0, "url": "https://reddit.com/r/dataisugly/comments/bd4rl1/graphing_the_popularity_of_depression_cherrys/", "title": "Graphing the popularity of Depression Cherry's songs on Spotify", "author": "NullOfficer", "popularity_score": 163, "phash": "b890472fc36f8473", "duplicated_images": ["reddit/BeachHouse/bd2c6f_0"], "duplicated_posts": [{"url": "https://reddit.com/r/BeachHouse/comments/bd2c6f/graphing_the_popularity_of_depression_cherrys/", "title": "Graphing the popularity of Depression Cherry's songs on Spotify", "author": "cylindricalcat", "post_id": "reddit/BeachHouse/bd2c6f", "datetime": 1555245520.0}], "labels": ["data:categorical", "data:percentage", "domain:entertainment", "effect:confuesed", "fault:wronglabel", "form:barchart"], "remarks": "Not too bad. Less decimal points and add \"%\" for the item labels."}