{"id": "brwi4a", "image_name": "brwi4a_0", "image_path": "preview/brwi4a_0.png", "thumbnail_path": "thumbnail/brwi4a_0.jpg", "datetime": 1558571442.0, "url": "https://reddit.com/r/dataisugly/comments/brwi4a/tv_show_imdb_user_rating_trajectories_oc/", "title": "TV Show IMDb User Rating Trajectories [OC]", "author": "", "source": "dataisugly", "source_url": "https://www.reddit.com/r/dataisugly", "source_platform": "reddit", "popularity_score": 40, "phash": "ae0b3349271be41f", "duplicated_images": ["reddit/dataisbeautiful/brnktf_0"], "labels": ["data:ordinal", "data:quantitative", "fault:axis", "fault:label", "form:linechart", "layout:juxtaposition"], "remarks": "Missing axes labels.\nEpisodes are ordinal not continuous."}