{"id": "ccvzbi", "post_id": "reddit/dataisugly/ccvzbi", "image_name": "ccvzbi_0", "image_path": "preview/ccvzbi_0.jpg", "thumbnail_path": "thumbnail/ccvzbi_0.jpg", "datetime": 1563060166.0, "url": "https://reddit.com/r/dataisugly/comments/ccvzbi/the_red_and_blue_dont_mean_republicandemocrat_and/", "title": "The red and blue don't mean Republican/Democrat, and 16% and 12% are each 50%? 36% of who?", "author": "RamonaLittle", "popularity_score": 424, "phash": "edc2d23de4521fc0", "duplicated_images": [], "duplicated_posts": [], "labels": ["data:categorical", "data:percentage", "data:timeseries", "domain:politics", "effect:distorted", "fault:labelconfuse", "fault:scale:inconsistent", "form:barchart"], "remarks": "16% has the same length with 12%.\nWhich label is which and what do they mean?"}