{"id": "civ9hj", "image_name": "civ9hj_0", "image_path": "preview/civ9hj_0.jpg", "thumbnail_path": "thumbnail/civ9hj_0.jpg", "datetime": 1564316941.0, "url": "https://reddit.com/r/dataisugly/comments/civ9hj/number_of_phd_students_at_tartu_university/", "title": "Number of PhD students at Tartu University", "author": "danaubin", "source": "dataisugly", "source_url": "https://www.reddit.com/r/dataisugly", "source_platform": "reddit", "popularity_score": 532, "phash": "ec9693491a3c6d65", "duplicated_images": [], "labels": ["data:quantitative", "data:timeseries", "fault:color", "fault:label", "fault:legend", "form:piechart"], "remarks": ""}