{"id": "del1ez", "image_name": "del1ez_0", "image_path": "bad-vis-images/preview/del1ez_0.jpg", "thumbnail_path": "bad-vis-images/thumbnail/del1ez_0.jpg", "datetime": 1570462287.0, "url": "https://reddit.com/r/dataisugly/comments/del1ez/election_results_in_portugal_nothing_is_to_scale/", "title": "Election results in Portugal. Nothing is to scale, and apparently 1 is bigger than 3.", "author": "Anforas", "source": "dataisugly", "source_url": "https://www.reddit.com/r/dataisugly", "source_platform": "reddit", "popularity_score": 2039, "phash": "83817c7f5b58e087", "labels": ["data:categorical", "data:quantitative", "fault:scale:inconsistent", "form:barchart", "media:tv"], "remarks": ""}