{"id": "didsb4", "post_id": "reddit/dataisugly/didsb4", "image_name": "didsb4_0", "image_path": "preview/didsb4_0.jpg", "thumbnail_path": "thumbnail/didsb4_0.jpg", "datetime": 1571170881.0, "url": "https://reddit.com/r/dataisugly/comments/didsb4/dscc_dem_senate_campaign_committee_doesnt_know/", "title": "DSCC (dem senate campaign committee) doesn\u2019t know how to do bar graphs", "author": "pongpingpongpingpong", "popularity_score": 413, "phash": "bfc092b4e1b9c41b", "duplicated_images": [], "duplicated_posts": [], "labels": ["data:categorical", "data:percentage", "domain:politics", "effect:distorted", "fault:scale:inconsistent", "form:barchart"], "remarks": "5% is half of 28%."}