{"id": "eq1hin", "post_id": "reddit/dataisugly/eq1hin", "image_name": "eq1hin_0", "image_path": "preview/eq1hin_0.png", "thumbnail_path": "thumbnail/eq1hin_0.jpg", "datetime": 1579273415.0, "url": "https://reddit.com/r/dataisugly/comments/eq1hin/found_this_on_the_bbcs_website_today/", "title": "Found this on the BBC's website today", "author": "BrendanW84", "popularity_score": 426, "phash": "cf348fca308f702b", "duplicated_images": [], "duplicated_posts": [], "labels": ["data:categorical", "domain:public", "effect:confuesed", "fault:axis:label", "fault:cannotunderstand", "fault:data:hypothetical", "fault:legibility", "form:linechart"], "remarks": "Missing axis labels.\nIllegible text.\nData is hypothetical.\nCannot understand."}