{"id": "gati1h", "post_id": "reddit/dataisugly/gati1h", "image_name": "gati1h_0", "image_path": "preview/gati1h_0.png", "thumbnail_path": "thumbnail/gati1h_0.jpg", "datetime": 1588244186.0, "url": "https://reddit.com/r/dataisugly/comments/gati1h/when_you_ignore_people_who_havent_heard_of_it_you/", "title": "When you ignore people who haven't heard of it, you can portray the developing world as hotbeds of Holocaust denial.", "author": "civver3", "popularity_score": 928, "phash": "ee6991b0a74e4e07", "duplicated_images": ["reddit/MapPorn/gac5gq_0"], "duplicated_posts": [{"url": "https://reddit.com/r/MapPorn/comments/gac5gq/percentage_of_people_who_believe_the_holocaust/", "title": "Percentage of People Who Believe the Holocaust Happened by Country", "author": "Dmitriyungern", "post_id": "reddit/MapPorn/gac5gq", "datetime": 1588176127.0}], "labels": ["data:geospatial", "data:percentage", "domain:international", "effect:distorted", "fault:colorcorrelation", "fault:data:missingvalues", "form:choropleth"], "remarks": "Using strips to represent missing data is confused as the same category as the neighbors."}